docgui/__init__.py
docgui/application.py
docgui/usage_parser.py
docgui/utils.py
docgui-1.0.0.dist-info/METADATA
docgui-1.0.0.dist-info/RECORD
docgui-1.0.0.dist-info/WHEEL
docgui-1.0.0.dist-info/entry_points.txt
docgui-1.0.0.dist-info/top_level.txt
