Metadata-Version: 2.1
Name: docgui
Version: 1.0.0
Summary: Turn docopt programs into GUI applications
Home-page: https://github.com/Afoucaul/docgui
Author: Armand Foucault
Author-email: armand.foucault@telecom-bretagne.eu
License: UNKNOWN
Platform: UNKNOWN
